tracebloc_package/__init__.py
tracebloc_package/linkModelDataSet.py
tracebloc_package/user.py
tracebloc_package/model_file_checks/__init__.py
tracebloc_package/model_file_checks/functional_checks.py
tracebloc_package/model_file_checks/pytorch_checks.py
tracebloc_package/model_file_checks/sklearn_checks.py
tracebloc_package/model_file_checks/tensorflow_checks.py
tracebloc_package/upload_model_classes/__init__.py
tracebloc_package/upload_model_classes/model_upload.py
tracebloc_package/upload_model_classes/skl_tabular_classifier.py
tracebloc_package/upload_model_classes/skl_tabular_regression.py
tracebloc_package/upload_model_classes/tf_image_classifier.py
tracebloc_package/upload_model_classes/torch_image_classifier.py
tracebloc_package/upload_model_classes/torch_key_point_detector.py
tracebloc_package/upload_model_classes/torch_object_detector.py
tracebloc_package/upload_model_classes/torch_semantic_segmentation.py
tracebloc_package/upload_model_classes/torch_tabular_classifier.py
tracebloc_package/upload_model_classes/torch_tabular_regression.py
tracebloc_package/upload_model_classes/torch_text_classifier.py
tracebloc_package/utils/__init__.py
tracebloc_package/utils/check_parameters.py
tracebloc_package/utils/constants.py
tracebloc_package/utils/detection_utils.py
tracebloc_package/utils/feature_dict.py
tracebloc_package/utils/general_utils.py
tracebloc_package/utils/key_point_detection_utils.py
tracebloc_package/utils/model_upload_utils.py
tracebloc_package/utils/semantic_segmentation_utils.py
tracebloc_package/utils/tabular_classification_utils.py
tracebloc_package/utils/tabular_regression_utils.py
tracebloc_package/utils/text_classification_utils.py
tracebloc_package/utils/user_message_constants.py
tracebloc_package/utils/yololoss.py
tracebloc_package-0.6.30.dist-info/METADATA
tracebloc_package-0.6.30.dist-info/WHEEL
tracebloc_package-0.6.30.dist-info/top_level.txt
tracebloc_package-0.6.30.dist-info/RECORD
