Metadata-Version: 2.4
Name: tracebloc_package
Version: 0.6.30
Summary: Package required to run Tracebloc jupyter notebook to create experiment
Home-page: https://gitlab.com/tracebloc/tracebloc-py-package
Author: Tracebloc
Author-email: lukas@tracebloc.io
License: MIT
Requires-Python: >=3
Requires-Dist: absl-py
Requires-Dist: dill
Requires-Dist: pandas
Requires-Dist: peft
Requires-Dist: protobuf
Requires-Dist: requests
Requires-Dist: rich
Requires-Dist: silence-tensorflow
Requires-Dist: scikit-learn
Requires-Dist: tensorflow
Requires-Dist: tensorflow-datasets
Requires-Dist: termcolor
Requires-Dist: timm
Requires-Dist: torch
Requires-Dist: torchlightning
Requires-Dist: torchmetrics
Requires-Dist: torchvision
Requires-Dist: tqdm
Requires-Dist: transformers
Requires-Dist: twine
Requires-Dist: xgboost
Requires-Dist: catboost
Requires-Dist: lightgbm
Dynamic: author
Dynamic: author-email
Dynamic: description
Dynamic: description-content-type
Dynamic: home-page
Dynamic: license
Dynamic: requires-dist
Dynamic: requires-python
Dynamic: summary
